LeptonWeighter/libLeptonWeighter.dylib
LeptonWeighter/LeptonWeighter.so
LeptonWeighter/__init__.py
LeptonWeighter/libLeptonWeighter.1.dylib
LeptonWeighter/libLeptonWeighter.1.1.5.dylib
LeptonWeighter/.dylibs/libhdf5.310.5.1.dylib
LeptonWeighter/.dylibs/libcfitsio.4.6.3.dylib
LeptonWeighter/.dylibs/libaec.0.1.4.dylib
LeptonWeighter/.dylibs/libhdf5_cpp.310.0.6.dylib
LeptonWeighter/.dylibs/libsz.2.0.1.dylib
LeptonWeighter/.dylibs/libhdf5_hl.310.0.6.dylib
LeptonWeighter/.dylibs/libphotospline.2.3.1.dylib
include/LeptonWeighter/Weighter.h
include/LeptonWeighter/Utils.h
include/LeptonWeighter/MetaWeighter.h
include/LeptonWeighter/Event.h
include/LeptonWeighter/LeptonInjectorConfigReader.h
include/LeptonWeighter/Constants.h
include/LeptonWeighter/Flux.h
include/LeptonWeighter/CrossSection.h
include/LeptonWeighter/ParticleType.h
include/LeptonWeighter/Generator.h
leptonweighter-1.1.5.dist-info/RECORD
leptonweighter-1.1.5.dist-info/WHEEL
leptonweighter-1.1.5.dist-info/METADATA
leptonweighter-1.1.5.dist-info/licenses/LICENSE
lib/pkgconfig/leptonweighter.pc
