Metadata-Version: 2.2
Name: LeptonWeighter
Version: 1.1.5
Summary: Weights injected neutrino final states to neutrino fluxes
Author-Email: =?utf-8?q?Carlos_A=2E_Arg=C3=BCelles_Delgado?= <carguelles@fas.harvard.edu>
License:                    GNU LESSER GENERAL PUBLIC LICENSE
Classifier: Programming Language :: Python :: 3
Classifier: Programming Language :: C++
Classifier: License :: OSI Approved :: GNU Lesser General Public License v3 (LGPLv3)
Classifier: Topic :: Scientific/Engineering :: Physics
Requires-Python: >=3.8
Requires-Dist: numpy
Provides-Extra: hdf5
Requires-Dist: h5py; extra == "hdf5"
Provides-Extra: tables
Requires-Dist: tables; extra == "tables"
